T5_worldgen/__init__.py
T5_worldgen/mapping_region.py
T5_worldgen/planet.py
T5_worldgen/pseudohex.py
T5_worldgen/star.py
T5_worldgen/system.py
T5_worldgen/trade_codes.py
T5_worldgen/upp.py
T5_worldgen/util.py
T5_worldgen-0.1.7.dist-info/DESCRIPTION.rst
T5_worldgen-0.1.7.dist-info/METADATA
T5_worldgen-0.1.7.dist-info/RECORD
T5_worldgen-0.1.7.dist-info/WHEEL
T5_worldgen-0.1.7.dist-info/metadata.json
T5_worldgen-0.1.7.dist-info/top_level.txt
