Metadata-Version: 2.0
Name: T5-worldgen
Version: 0.1.7
Summary: Python modules to generate Traveller 5 world(s)
Home-page: https://github.com/makhidkarun/T5_worldgen
Author: Arthur Green
Author-email: arthur.green045@gmail.com
License: MIT
Platform: UNKNOWN
